odoo/addons/product_pricelist_margin/README.rst
odoo/addons/product_pricelist_margin/__init__.py
odoo/addons/product_pricelist_margin/__manifest__.py
odoo/addons/product_pricelist_margin/i18n/fr.pot
odoo/addons/product_pricelist_margin/i18n/it.po
odoo/addons/product_pricelist_margin/i18n/product_pricelist_margin.pot
odoo/addons/product_pricelist_margin/i18n/product_pricelist_margins.pot
odoo/addons/product_pricelist_margin/models/__init__.py
odoo/addons/product_pricelist_margin/models/product_pricelist_item.py
odoo/addons/product_pricelist_margin/readme/CONTRIBUTORS.md
odoo/addons/product_pricelist_margin/readme/DESCRIPTION.md
odoo/addons/product_pricelist_margin/readme/USAGE.md
odoo/addons/product_pricelist_margin/static/description/icon.png
odoo/addons/product_pricelist_margin/static/description/index.html
odoo/addons/product_pricelist_margin/static/description/pricelist_item.png
odoo/addons/product_pricelist_margin/tests/__init__.py
odoo/addons/product_pricelist_margin/tests/test_margin.py
odoo/addons/product_pricelist_margin/views/product_pricelist_item_views.xml
odoo/addons/product_pricelist_margin/views/product_pricelist_views.xml
odoo_addon_product_pricelist_margin-18.0.1.0.0.2.dist-info/METADATA
odoo_addon_product_pricelist_margin-18.0.1.0.0.2.dist-info/WHEEL
odoo_addon_product_pricelist_margin-18.0.1.0.0.2.dist-info/top_level.txt
odoo_addon_product_pricelist_margin-18.0.1.0.0.2.dist-info/RECORD
